neptune_apex_classic/__init__.py
neptune_apex_classic/connection.py
neptune_apex_classic/outlet.py
neptune_apex_classic/probe.py
neptune_apex_classic-0.1.0.dist-info/LICENSE
neptune_apex_classic-0.1.0.dist-info/METADATA
neptune_apex_classic-0.1.0.dist-info/WHEEL
neptune_apex_classic-0.1.0.dist-info/top_level.txt
neptune_apex_classic-0.1.0.dist-info/RECORD
