Metadata-Version: 2.1
Name: neptune-apex-classic
Version: 0.1.0
Summary: Python tooling to control a classic Neptune Apex on your LAN
Author-email: Chris Sammis <csammis@gmail.com>
Project-URL: Homepage, https://github.com/csammis/neptune_apex_classic
Project-URL: Bug Tracker, https://github.com/csammis/neptune_apex_classic/issues
Classifier: Programming Language :: Python :: 3
Classifier: License :: OSI Approved :: MIT License
Classifier: Operating System :: OS Independent
Requires-Python: >=3.10
License-File: LICENSE
Requires-Dist: beautifulsoup4 (==4.11.2)
Requires-Dist: aiohttp (==3.8.4)
Requires-Dist: lxml (==4.9.2)
